imbue_desktop/__init__.py
imbue_desktop/error_utils.py
imbue_desktop/errors.py
imbue_desktop/foreman.py
imbue_desktop/local_data.py
imbue_desktop/main.py
imbue_desktop/qt.py
imbue_desktop/utils.py
imbue_desktop/local_sync_client/__init__.py
imbue_desktop/local_sync_client/constants.py
imbue_desktop/local_sync_client/core.py
imbue_desktop/local_sync_client/data_types.py
imbue_desktop/local_sync_client/file_watcher.py
imbue_desktop/local_sync_client/main.py
imbue_desktop/local_sync_client/message_types.py
imbue_desktop/local_sync_client/server_message_stream.py
imbue_desktop/local_sync_client/server_message_stream_test.py
imbue_desktop/local_sync_client/utils.py
imbue_desktop-0.0.9.dist-info/licenses/LICENSE
imbue_desktop-0.0.9.dist-info/METADATA
imbue_desktop-0.0.9.dist-info/WHEEL
imbue_desktop-0.0.9.dist-info/entry_points.txt
imbue_desktop-0.0.9.dist-info/top_level.txt
imbue_desktop-0.0.9.dist-info/RECORD
