Metadata-Version: 2.4
Name: imbue-desktop
Version: 0.0.9
Summary: A thin client for the Imbue AI coding tool.
Author-email: Imbue <imbue@imbue.com>
License-Expression: MIT
Project-URL: homepage, https://imbue.com/
Requires-Python: >=3.11
License-File: LICENSE
Requires-Dist: aiohttp>=3.9.3
Requires-Dist: anyio
Requires-Dist: toml
Requires-Dist: imbue-core==0.0.9
Requires-Dist: loguru>=0.7.0
Requires-Dist: psutil>=5.9.5
Requires-Dist: pydantic>=2.10.6
Requires-Dist: pyside6>=6.8.2.1
Requires-Dist: tenacity>=8.2.2
Requires-Dist: typer>=0.12.3
Requires-Dist: typing-extensions>=4.12.2
Requires-Dist: watchdog>=4.0.1
Requires-Dist: sentry-sdk>=2.22.0
Requires-Dist: pyjwt>=2.8.0
Requires-Dist: platformdirs>=4.3.6
Dynamic: license-file
